setup.py
githubxml/__init__.py
githubxml/usuario.py
githubxml.egg-info/PKG-INFO
githubxml.egg-info/SOURCES.txt
githubxml.egg-info/dependency_links.txt
githubxml.egg-info/not-zip-safe
githubxml.egg-info/requires.txt
githubxml.egg-info/top_level.txt