Metadata-Version: 1.1
Name: githubxml
Version: 0.2
Summary: Projeto para fazer versão xml da API do Github
Home-page: https://github.com/pythonprobr/pypraticot04
Author: Renzo Nuccitelli
Author-email: renzo.n@gmail.com
License: BSD
Platform: UNKNOWN
Classifier: Development Status :: 4 - Beta
Classifier: Environment :: Web Environment
Classifier: Intended Audience :: Developers
Classifier: License :: OSI Approved :: BSD License
Classifier: Operating System :: OS Independent
Classifier: Programming Language :: Python
Classifier: Framework :: Paste
